DirtyIO/__init__.py
DirtyIO/dirtyReader.py
DirtyIO/dirtyWriter.py
DirtyIO_A13XIS-1.0.0.dist-info/LICENSE
DirtyIO_A13XIS-1.0.0.dist-info/METADATA
DirtyIO_A13XIS-1.0.0.dist-info/WHEEL
DirtyIO_A13XIS-1.0.0.dist-info/top_level.txt
DirtyIO_A13XIS-1.0.0.dist-info/RECORD
