Metadata-Version: 2.1
Name: DirtyIO-A13XIS
Version: 1.0.0
Summary: Dirty quick binary file management library
Home-page: https://github.com/A13XIS/dirtyio
Author: Lex Sternin
Author-email: allseeingstar@googlemail.com
License: UNKNOWN
Platform: UNKNOWN
Classifier: Programming Language :: Python :: 3
Classifier: License :: OSI Approved :: GNU General Public License v3 (GPLv3)
Classifier: Operating System :: OS Independent
